{
  "values": [
    44,
    19,
    11,
    10,
    5,
    5,
    2,
    2,
    1,
    1
  ],
  "labels": [
    "Electronics",
    "Physical & Electronic media",
    "Sports & Outdoors",
    "Clothing & Apparel",
    "Tools & Garden",
    "Shoes & Accessories",
    "Pharmacy",
    "Office Supplies",
    "Auto Parts",
    "Health & Beauty"
  ],
  "settings": {
    "valuesFont": "arial",
    "valuesSize": 12,
    "valuesColor": null,
    "valuesDisplay": "percentage",
    "valuesOrder": "descending",
    "valuesDec": 0,
    "labelsFont": "arial",
    "labelsSize": 12,
    "labelsColor": "#333333",
    "labelsInner": false,
    "labelsBold": false,
    "labelsMinFontSize": 10,
    "groups": null,
    "groupsFont": "arial",
    "groupsFontColor": "#333333",
    "groupsSize": 10,
    "groupsBold": false,
    "groupsColor": null,
    "groupsNames": null,
    "groupsSums": null,
    "groupsCounts": null,
    "groupLabelsMinFontSize": 8,
    "title": "Amazon Australia - category share estimate",
    "titleFontFamily": "arial",
    "titleFontSize": 16,
    "titleFontColor": "#333333",
    "titleTopPadding": 0,
    "titleBold": false,
    "prefix": null,
    "suffix": "%",
    "orderControl": false,
    "gradient": false,
    "innerRadius": "0%",
    "minAngle": 0.003,
    "borderColor": "none"
  }
}
